models/__init__.py
models/checkout.py
models/common.py
models/disbursement.py
models/paginated_response.py
models/payment.py
models/remittance.py
resources/__init__.py
resources/base.py
resources/disbursements.py
resources/payments.py
resources/remittances.py
resources/sessions.py
yabetoo_sdk-0.1.0.dist-info/METADATA
yabetoo_sdk-0.1.0.dist-info/WHEEL
yabetoo_sdk-0.1.0.dist-info/top_level.txt
yabetoo_sdk-0.1.0.dist-info/RECORD
