Metadata-Version: 2.4
Name: yabetoo-sdk
Version: 0.1.0
Summary: Yabetoo Python SDK
Home-page: https://github.com/yabetoo/yabetoo-py
Author: Yabetoo
Author-email: contact@yabetoopay.com
License: MIT
Project-URL: Homepage, https://github.com/yabetoo/sdk-py
Project-URL: Source, https://github.com/yabetoo/sdk-py
Requires-Python: >=3.7
Dynamic: author-email
Dynamic: home-page
Dynamic: requires-python
